rnz_news/__init__.py
tests/__init__.py
rnz_news-1.0.1.dist-info/METADATA
rnz_news-1.0.1.dist-info/WHEEL
rnz_news-1.0.1.dist-info/top_level.txt
rnz_news-1.0.1.dist-info/RECORD
