Metadata-Version: 2.1
Name: rnz-news
Version: 1.0.1
Summary: Retrieve RNZ news.
Home-page: https://github.com/aguang-xyz/rnz-news
Author: Guangrui Wang
Author-email: aguang.xyz@gmail.com
License: UNKNOWN
Platform: UNKNOWN
Classifier: Programming Language :: Python :: 3
Classifier: License :: OSI Approved :: MIT License
Classifier: Operating System :: OS Independent
Requires-Python: >= 3.8
